sources/Contadores/cont_0a9.vhd
library IEEE;
use IEEE.std_logic_1164.all;
use IEEE.numeric_std.all;

entity contador0a9 is
    port (
        t_in, rst, load: in std_logic;
        t_out0, t_out1: out std_logic_vector(3 downto 0)
        );

end entity;

architecture contador0a9 of contador0a9 is
    
    signal contador : unsigned(3 downto 0) := (others => '0');
    signal t_out0_s, t_out1_s: std_logic_vector(3 downto 0):= (others => '0');
    signal slct: std_logic := '0';
    
    begin
        process(t_in, rst, load)
        begin
            if rising_edge(rst) or falling_edge(load) then
                contador <= (others => '0');
            elsif rising_edge(t_in) then
                if contador = 9 then
                    contador <= (others => '0');
                else
                    contador <= contador + 1;
                end if;
            end if;

            if rising_edge(load) then
                
                    if slct='0' then 
                    t_out0_s <= std_logic_vector(contador);
                    slct <= not slct;

                    else
                    t_out1_s <= std_logic_vector(contador);
                    slct <= not slct;
                end if;
            
            end if;
        end process;
        
        t_out0 <= t_out0_s;
        t_out1 <= t_out1_s;
    end architecture;

JOUSAMRON PROYECTO/JOUSAMRON PROYECTO.srcs/sources_1/imports/sources/Test/testbench-cont09.vhd
library IEEE;
use IEEE.std_logic_1164.all;
use IEEE.numeric_std.all;

entity testbench is
end entity;

architecture behavioral of testbench is
    
    

    signal rst, load: std_logic := '0';
    signal t: std_logic := '0';
    signal data_out0, data_out1: std_logic_vector(3 downto 0) := (others => '0');


    begin

    pot: entity work.contador0a9
        port map(
            t_in => t,
            rst => rst,
            load=> load,
            t_out0 => data_out0,
            t_out1 => data_out1
     
        );
    
    process
    begin
        wait for 50 ms;
        for i in 0 to 9 loop
            t<= not t;
            wait for 500 us;
            end loop;
        load<= '1';
        wait for 10 us;
        load<= '0';
        wait for 50 ms;
        for i in 0 to 13 loop
            t<= not t;
            wait for 500 us;
            end loop;
        load<= '1';
        wait for 50 us;
        load<= '0';
        wait for 50 ms;
    wait;
    end process;    
end architecture;

sources/Dumps/cont09-dump.vcd
$date
  Mon May 15 14:35:27 2023
$end
$version
  GHDL v0
$end
$timescale
  1 fs
$end
$scope module standard $end
$upscope $end
$scope module std_logic_1164 $end
$upscope $end
$scope module numeric_std $end
$upscope $end
$scope module testbench $end
$var reg 1 ! rst $end
$var reg 1 " load $end
$var reg 1 # t $end
$var reg 4 $ data_out0[3:0] $end
$var reg 4 % data_out1[3:0] $end
$scope module pot $end
$var reg 1 & t_in $end
$var reg 1 ' rst $end
$var reg 1 ( load $end
$var reg 4 ) t_out0[3:0] $end
$var reg 4 * t_out1[3:0] $end
$var reg 4 + contador[3:0] $end
$var reg 4 , t_out0_s[3:0] $end
$var reg 4 - t_out1_s[3:0] $end
$var reg 1 . slct $end
$upscope $end
$upscope $end
$enddefinitions $end
#0
0!
0"
0#
b0000 $
b0000 %
0&
0'
0(
b0000 )
b0000 *
b0000 +
b0000 ,
b0000 -
0.
#50000000000000
1#
1&
b0001 +
#50500000000000
0#
0&
#51000000000000
1#
1&
b0010 +
#51500000000000
0#
0&
#52000000000000
1#
1&
b0011 +
#52500000000000
0#
0&
#53000000000000
1#
1&
b0100 +
#53500000000000
0#
0&
#54000000000000
1#
1&
b0101 +
#54500000000000
0#
0&
#55000000000000
1"
b0101 $
1(
b0101 )
b0101 ,
1.
#55010000000000
0"
0(
b0000 +
#105010000000000
1#
1&
b0001 +
#105510000000000
0#
0&
#106010000000000
1#
1&
b0010 +
#106510000000000
0#
0&
#107010000000000
1#
1&
b0011 +
#107510000000000
0#
0&
#108010000000000
1#
1&
b0100 +
#108510000000000
0#
0&
#109010000000000
1#
1&
b0101 +
#109510000000000
0#
0&
#110010000000000
1#
1&
b0110 +
#110510000000000
0#
0&
#111010000000000
1#
1&
b0111 +
#111510000000000
0#
0&
#112010000000000
1"
b0111 %
1(
b0111 *
b0111 -
0.
#112060000000000
0"
0(
b0000 +
