sources/State Machines/global.vhd
library IEEE;
use IEEE.std_logic_1164.all;
use IEEE.numeric_std.all;

entity global is
    port(

        rst: in std_logic;
        start, stop_in : in std_logic;
        door: in std_logic;
        t_in0: in std_logic_vector(3 downto 0);
        t_in1: in std_logic_vector(3 downto 0);

        w_in: in std_logic_vector(3 downto 0);

        enable_out: out std_logic

    );
end entity;

architecture Behavioral of global is
    type states is (running, stopped);
    signal prev_state: states:=stopped;
    signal next_state: states;
    signal t,w,safety: integer:=0;
    begin
    
    process(t_in0, t_in1, w_in,rst)
    begin
        if rising_edge(rst) then
            t<=0;
            w<=0;
            safety<=0;
        else
        t<= to_integer(unsigned(t_in1))*10 + to_integer(unsigned(t_in0));
        w<= to_integer(unsigned(w_in)*10);
        safety<=to_integer(unsigned(t_in1))*10 + to_integer(unsigned(t_in0))+to_integer(unsigned(w_in)*10);
        end if;
        
    end process;
    
    process(prev_state, start, stop_in, door, t,w,safety)

    begin
        if prev_state=running and (door='1' or rising_edge(stop_in)) then
            prev_state<=next_state;

        elsif prev_state=stopped and (rising_edge(start) and (t>0) and (safety<100) and (door='0')) then
            prev_state<=next_state;
        end if;

    end process;

    process(prev_state)
    begin
        case prev_state is
            when stopped =>
                next_state <= running;
            when running =>
                next_state <= stopped;
            end case;
    end process;

    enable_out <= '1' when prev_state=running else '0';
    end architecture;

sources/Test/testbench-global.vhd
library IEEE;
use IEEE.std_logic_1164.all;
use IEEE.numeric_std.all;

entity testbench is
end entity;

architecture Behavioral of testbench is
    
    signal rst,start, stopin, door, en: std_logic:='0';
    signal tin0,tin1,win: std_logic_vector(3 downto 0):="0000";

    begin
    glb:entity work.global port map(
   
    rst => rst,
        start => start,
        stop_in => stopin,
        door => door,
        enable_out => en,
        t_in0 => tin0,
        t_in1 => tin1,
        w_in => win
    );

    process
    begin

        wait for 10 ms;

        stopin <= '0';
        door <= '0';
        tin0 <= "0000";
        tin1 <= "0011";
        win <= "0001";
        wait for 10 ms;

        start <= '1';
        wait for 10 us;
        start <= '0';

        wait for 10 ms;
        door <= '1';
        wait for 10 ms;
        door <= '0';

        start <= '1';
        wait for 10 us;
        start <= '0';

        wait for 20 ms;
        stopin <= '1';
        wait for 10 us;
        stopin <= '0';

        wait for 10 ms;
        
        tin0 <= "0001";
        tin1 <= "0101";
        win <= "1000";

        wait for 10 ms;
        start <= '1';
        wait for 10 us;
        start <= '0';

        wait for 10 ms;
    wait;
    end process;

    end architecture;

sources/Dumps/global-dump.vcd
$date
  Wed May 17 09:41:17 2023
$end
$version
  GHDL v0
$end
$timescale
  1 fs
$end
$scope module standard $end
$upscope $end
$scope module std_logic_1164 $end
$upscope $end
$scope module numeric_std $end
$upscope $end
$scope module testbench $end
$var reg 1 ! rst $end
$var reg 1 " start $end
$var reg 1 # stopin $end
$var reg 1 $ door $end
$var reg 1 % en $end
$var reg 4 & tin0[3:0] $end
$var reg 4 ' tin1[3:0] $end
$var reg 4 ( win[3:0] $end
$scope module glb $end
$var reg 1 ) rst $end
$var reg 1 * start $end
$var reg 1 + stop_in $end
$var reg 1 , door $end
$var reg 4 - t_in0[3:0] $end
$var reg 4 . t_in1[3:0] $end
$var reg 4 / w_in[3:0] $end
$var reg 1 0 enable_out $end
$comment prev_state is not handled $end
$comment next_state is not handled $end
$var integer 32 1 t $end
$var integer 32 2 w $end
$var integer 32 3 safety $end
$upscope $end
$upscope $end
$enddefinitions $end
#0
0!
0"
0#
0$
0%
b0000 &
b0000 '
b0000 (
0)
0*
0+
0,
b0000 -
b0000 .
b0000 /
00
b0 1
b0 2
b0 3
#10000000000000
b0011 '
b0001 (
b0011 .
b0001 /
b11110 1
b1010 2
b101000 3
#20000000000000
1"
1%
1*
10
#20010000000000
0"
0*
#30010000000000
1$
0%
1,
00
#40010000000000
1"
0$
1%
1*
0,
10
#40020000000000
0"
0*
#60020000000000
1#
0%
1+
00
#60030000000000
0#
0+
#70030000000000
b0001 &
b0101 '
b1000 (
b0001 -
b0101 .
b1000 /
b110011 1
b1010000 2
b10000011 3
#80030000000000
1"
1*
#80040000000000
0"
0*
