JOUSAMRON MICROONDAS/JOUSAMRON MICROONDAS.srcs/sources_1/imports/sources/State Machines/potencia.vhd
library IEEE;
use IEEE.std_logic_1164.all;

entity potencia is
    port(
    --clk: in std_logic;
    w_in: in std_logic;
    en: in std_logic;
    w_out_0: out STD_LOGIC_VECTOR(3 downto 0);
    w_out_1: out STD_LOGIC_VECTOR(3 downto 0);
    pot_out: out std_logic_vector(7 downto 0)
    );
end entity;

architecture Behavioral of potencia is
    type states is (W1,W2,W3,W4,W5,W6,W7,W8);
    signal prev_state: states:=W1;
    signal next_state: states;
    signal w_out_0_s: STD_LOGIC_VECTOR(3 downto 0):="0000";
    begin

    process(w_in, en)
    begin
     if en='0' then
            if rising_edge(w_in) then
                prev_state <= next_state;
          end if;
     end if;
    end process;


    process(prev_state)
    begin
        case prev_state is
            when W1 => 
                w_out_1 <= "0001";
                next_state<=W2;
                pot_out <= "00000001";
            when W2 => 
                w_out_1 <= "0010";
                next_state<=W3;
                pot_out <= "00000011";
            when W3 => 
                w_out_1 <= "0011";
                next_state<=W4;
                pot_out <= "00000111";
            when W4 => 
                w_out_1 <= "0100";
                next_state<=W5;
                pot_out <= "00001111";
            when W5 => 
                w_out_1 <= "0101";
                next_state<=W6;
                pot_out <= "00011111";
            when W6 => 
                w_out_1 <= "0110";
                next_state<=W7;
                pot_out <= "00111111";
            when W7 =>
                w_out_1 <= "0111"; 
                next_state<=W8;
                pot_out <= "01111111";
            when W8 =>
                w_out_1 <="1000";
                next_state<=W1;
                pot_out <= "11111111";
        end case;
    end process;
    
    

    w_out_0 <= w_out_0_s;
    end Behavioral;

sources/State Machines/global.vhd
library IEEE;
use IEEE.std_logic_1164.all;
use IEEE.numeric_std.all;

entity global is
    port(

      
        start, stop_in : in std_logic;
        door: in std_logic;
        t_in0: in std_logic_vector(3 downto 0);
        t_in1: in std_logic_vector(3 downto 0);

        w_in: in std_logic_vector(3 downto 0);

        enable_out: out std_logic

    );
end entity;

architecture Behavioral of global is
    type states is (running, stopped);
    signal prev_state: states:=stopped;
    signal next_state: states;
    signal t,w,safety: integer:=0;
    signal enable: std_logic;
    begin
    
    process(t_in0, t_in1, w_in, enable)
    begin
--        if rising_edge(stop_in) and enable='0' then
--            t<=0;
--            w<=0;
--            safety<=0;
--        else
        t<= to_integer(unsigned(t_in1))*10 + to_integer(unsigned(t_in0));
        w<= to_integer(unsigned(w_in)*10);
        safety<=to_integer(unsigned(t_in1))*10 + to_integer(unsigned(t_in0))+to_integer(unsigned(w_in)*10);
       -- end if;
        
    end process;
    
    process(prev_state, start, stop_in, door, t,w,safety)

    begin
        if prev_state=running and (door='1' or rising_edge(stop_in) or t=0) then
            prev_state<=next_state;

        elsif prev_state=stopped and (rising_edge(start) and (t>0) and (safety<=100) and (door='0')) then
            prev_state<=next_state;
        end if;

    end process;

    process(prev_state)
    begin
        case prev_state is
            when stopped =>
                next_state <= running;
            when running =>
                next_state <= stopped;
            end case;
    end process;

    enable <= '1' when prev_state=running else '0';
    enable_out<=enable;
    end architecture;

sources/Contadores/cont_des.vhd
library IEEE;
use IEEE.std_logic_1164.all;
use IEEE.numeric_std.all;

entity CONT_2DIG is
    
    port(
        clk: in std_logic;
        reset: in std_logic;
        enable: in std_logic;
      
           sr_r: out std_logic;
        dig_in0, dig_in1: in std_logic_vector(3 downto 0);
        num_out: out std_logic_vector(6 downto 0);
        dig0, dig1: out std_logic_vector(3 downto 0)
        
    );

    end entity;

architecture Behavioral of CONT_2DIG is
    
    signal count: integer range 90 downto 0 := 0;
    signal dig0_s,dig1_s: unsigned(3 downto 0) := (others => '0');
    signal r_s: std_logic:='0';

    begin

    process(clk, enable, count,r_s)
    begin
    
     if enable='0' then
   
        count <= to_integer(unsigned(dig_in1))*10 + to_integer(unsigned(dig_in0));
            dig0_s <= unsigned(dig_in0); 
            dig1_s <= unsigned(dig_in1);

      
    elsif enable='1' then    
         
        if rising_edge(clk) and count>0 then

            count <= count - 1;
            if dig0_s=0 then
                dig0_s <= to_unsigned(9,4);
                dig1_s <= dig1_s - 1;
            else 
                dig0_s <= dig0_s - 1;
            end if;
            
--            if count-1 = 0 then
--            sr_r<='1';
--            else
--            sr_r<='0';
--            end if;
            
        end if;         
     end if;

    end process;
    
    dig0 <= std_logic_vector(dig0_s);
    dig1 <= std_logic_vector(dig1_s);
    
  
    num_out <= std_logic_vector(to_unsigned(count,7));
    end architecture;

sources/SR_SP.vhd

library IEEE;
use IEEE.std_logic_1164.all;
use IEEE.numeric_std.all;

entity SR_SER_PAR is

port ( r, en : in std_logic;
      clk : in std_logic;

      d : in std_logic_vector(3 downto 0);
      d_in0, d_in1 : in std_logic_vector(3 downto 0);
      q_out0, q_out1 : out std_logic_vector(3 downto 0));

end entity;

architecture Behavioral of SR_SER_PAR is
    

        signal q: std_logic_vector(7 downto 0):="00000000";

        begin

        process(clk,r,en,d,q,d_in1,d_in0)
        begin
                 
        if(r='1' and en='0') then
   
                --q<="00000000"; 


            elsif r='0' and en='0' then
                if(rising_edge(clk)) then
                for i in 0 to 3 loop
                  q(3-i)<=q(7-i);
                  q(7-i)<=d(3-i);
                 
                end loop;
    
                end if;
            elsif r='0' and en='1' then
                q(7 downto 4)<=d_in1;
                q(3 downto 0)<=d_in0;
            end if;
        end process;
        q_out0<=q(3 downto 0);
        q_out1<=q(7 downto 4);
    end architecture;

sources/Contadores/cont_0a9.vhd
library IEEE;
use IEEE.std_logic_1164.all;
use IEEE.numeric_std.all;

entity contador0a9 is
    port (
        t_in, rst, load, start: in std_logic;
        t_out: out std_logic_vector(3 downto 0)

        );

end entity;

architecture contador0a9 of contador0a9 is
    
    signal contador : unsigned(3 downto 0) := (others => '0');
    signal t_out_s: std_logic_vector(3 downto 0):= (others => '0');

    
    begin
        process(t_in, rst,load, start)
        begin

            if rst='1' or start='1' then
                contador <= (others => '0');
                t_out_s <= std_logic_vector(contador);
              
            elsif rst='0' then 
            if  rising_edge(t_in) then
                if contador >= 9 then
                    contador <= (others => '0');
                else
                    contador <= contador + 1;
                    
                end if;
                
            end if;  
             t_out_s <= std_logic_vector(contador);
            end if;            
         
         
         
            
        end process;
        
        t_out <= t_out_s;

    end architecture;

sources/enable.vhd
library IEEE;
use IEEE.std_logic_1164.all;

entity enable_block is
    port(

        load, t, w: in std_logic;
        en  : in std_logic;
        load_o, t_o, w_o: out std_logic
    );
end entity;


architecture Behavioral of enable_block is
begin

    load_o<=load WHEN en='0' ELSE '0';
    t_o<=t WHEN en='0' ELSE '0';
    w_o<=w WHEN en='0' ELSE '0';
end architecture;

sources/mainT.vhd
library IEEE;
use IEEE.std_logic_1164.all;
use IEEE.numeric_std.all;

entity mainT is
    port(
        clk1hz : in std_logic;
        t_in, load, door,w : in std_logic;
        en: out std_logic;
        start,stop_in: in std_logic;
        --SAL_7SEG : out std_logic_vector(6 downto 0);
        --ANODOS: out std_logic_vector(3 downto 0);
        LED:out std_logic_vector(7 downto 0)
    );
end entity;

architecture Behavioral of mainT is

    --signal clk1hz, clk200khz: std_logic;
    
    signal t_in_s,t_in0, t_in1: std_logic_vector(3 downto 0);
  
    signal w_1, w_0: std_logic_vector(3 downto 0);
    
    signal dig0_out, dig1_out: std_logic_vector(3 downto 0);
    
    signal BCD1, BCD2, BCD3, BCD4: std_logic_vector(3 downto 0);

    signal load_s, w_s, t_s: std_logic;

    signal enable: std_logic;
    begin 
    

    
    -- clk1: entity work.DIV_1HZ
    --     port map(
    --         clk => clk,
    --         CLK_o => clk1hz
    --     );

    -- clk200k: entity work.DIV_VD
    --     port map(
    --         clk => clk,
    --         CLK_o => clk200khz
    --     );


    en_block: entity work.enable_block
        port map(

            en=> enable,
            load=>load,
            t=>t_in,
            w=>w,

            load_o=>load_s,
            w_o=>w_s,
            t_o=>t_s
        );

    cont0a9: entity work.contador0a9 
        port map(
            t_in => t_s,
            
            start=>start,
            load=>load_s,
            rst => stop_in,

            t_out => t_in_s
        );
    
        sr: entity work.SR_SER_PAR
        port map(
            r => stop_in,
           
            en=>enable,
            clk=> load_s,
            d=> t_in_s,
            d_in0=> dig0_out,
            d_in1=> dig1_out,
            q_out0=> t_in0,
            q_out1=> t_in1
        );

    cont_des: entity  work.CONT_2DIG
        port map(
            clk => clk1hz,
            reset => stop_in,
            enable => enable,

            dig_in0 => t_in0,
            dig_in1 => t_in1,

            num_out => open,

            dig0 => dig0_out,
            dig1 => dig1_out
        );

    global: entity work.global
        port map(

           
            start => start,
            stop_in => stop_in,
            door => door,
            
            w_in => w_1,
            
            t_in0 => dig0_out,
            t_in1 => dig1_out,

            enable_out => enable
        );
    
    pot: entity work.potencia
        port map(

            w_in => w_s,
            en=> enable,
            w_out_0 => w_0,
            w_out_1 => w_1,
            pot_out=> LED
        );

        -- VD: entity work.VIS_DIN_4DIG
        
        -- port map(
        -- clk=> clk200khz,
        -- ANODS=> ANODOS,
        -- SAL7SEG=> SAL_7SEG,
        -- BCD1=>dig1_out,
        -- BCD2=>dig0_out,
        -- BCD3=>w_1,
        -- BCD4=>w_0
        -- );
        en<=enable;
end architecture;

sources/Test/testbench-main.vhd
library IEEE;
use IEEE.std_logic_1164.all;
use IEEE.numeric_std.all;

entity testbench is
end entity;

architecture behavioral of testbench is
    
    signal clk: std_logic := '0';
    signal clk_period: time := 1 sec;


    signal load,t,w,door,start,stop_in,en: std_logic := '0';

    begin

    main: entity work.mainT
        port map(
            clk1hz => clk,
            load => load,
            t_in => t,
            w=> w,
            door => door,
            start => start,
            stop_in => stop_in,
            en => en

        );
    
        CLK_1HZ : process
    begin
    wait for clk_period / 2;
    if clk = '1' then
        clk <= '0';
    else
        clk <= '1';
    end if;
    end process;

    process
    begin

        wait for 2 sec;
        for i in 0 to 2 loop
        t<= '1';
        wait for 1 sec;
        t<= '0';    
        wait for 1 sec;
        end loop;

        wait for 2 sec;

        load <= '1';
        wait for 1 sec;
        load <= '0';

        wait for 2 sec;

        for i in 0 to 3 loop
        t<= '1';
        wait for 1 sec;
        t<= '0';    
        wait for 1 sec;
        end loop;

        wait for 2 sec;

        load <= '1';
        wait for 1 sec;
        load <= '0';

        wait for 2 sec;

        start <= '1';
        wait for 1 sec;
        start <= '0';


        wait for 2 sec;

        load <= '1';
        wait for 1 sec;
        load <= '0';


        wait for 2 sec;

        t <= '1';
        wait for 1 sec;
        t <= '0';


        wait for 2 sec;

        w <= '1';
        wait for 1 sec;
        w <= '0';


        wait for 2 sec;

        door <= '1';
        wait for 2 sec;
        load <= '0';

    wait;
    end process;    
end architecture;

sources/Dumps/main-dump.vcd
$date
  Wed May 24 23:01:26 2023
$end
$version
  GHDL v0
$end
$timescale
  1 fs
$end
$scope module standard $end
$upscope $end
$scope module std_logic_1164 $end
$upscope $end
$scope module numeric_std $end
$upscope $end
$scope module testbench $end
$var reg 1 ! clk $end
$comment clk_period is not handled $end
$var reg 1 " load $end
$var reg 1 # t $end
$var reg 1 $ w $end
$var reg 1 % door $end
$var reg 1 & start $end
$var reg 1 ' stop_in $end
$var reg 1 ( en $end
$scope module main $end
$var reg 1 ) clk1hz $end
$var reg 1 * t_in $end
$var reg 1 + load $end
$var reg 1 , door $end
$var reg 1 - w $end
$var reg 1 . en $end
$var reg 1 / start $end
$var reg 1 0 stop_in $end
$var reg 8 1 led[7:0] $end
$var reg 4 2 t_in_s[3:0] $end
$var reg 4 3 t_in0[3:0] $end
$var reg 4 4 t_in1[3:0] $end
$var reg 4 5 w_1[3:0] $end
$var reg 4 6 w_0[3:0] $end
$var reg 4 7 dig0_out[3:0] $end
$var reg 4 8 dig1_out[3:0] $end
$var reg 4 9 bcd1[3:0] $end
$var reg 4 : bcd2[3:0] $end
$var reg 4 ; bcd3[3:0] $end
$var reg 4 < bcd4[3:0] $end
$var reg 1 = load_s $end
$var reg 1 > w_s $end
$var reg 1 ? t_s $end
$var reg 1 @ enable $end
$scope module en_block $end
$var reg 1 A load $end
$var reg 1 B t $end
$var reg 1 C w $end
$var reg 1 D en $end
$var reg 1 E load_o $end
$var reg 1 F t_o $end
$var reg 1 G w_o $end
$upscope $end
$scope module cont0a9 $end
$var reg 1 H t_in $end
$var reg 1 I rst $end
$var reg 1 J load $end
$var reg 1 K start $end
$var reg 4 L t_out[3:0] $end
$var reg 4 M contador[3:0] $end
$var reg 4 N t_out_s[3:0] $end
$upscope $end
$scope module sr $end
$var reg 1 O r $end
$var reg 1 P en $end
$var reg 1 Q clk $end
$var reg 4 R d[3:0] $end
$var reg 4 S d_in0[3:0] $end
$var reg 4 T d_in1[3:0] $end
$var reg 4 U q_out0[3:0] $end
$var reg 4 V q_out1[3:0] $end
$var reg 8 W q[7:0] $end
$upscope $end
$scope module cont_des $end
$var reg 1 X clk $end
$var reg 1 Y reset $end
$var reg 1 Z enable $end
$var reg 1 [ sr_r $end
$var reg 4 \ dig_in0[3:0] $end
$var reg 4 ] dig_in1[3:0] $end
$var reg 7 ^ num_out[6:0] $end
$var reg 4 _ dig0[3:0] $end
$var reg 4 ` dig1[3:0] $end
$var integer 32 a count $end
$var reg 4 b dig0_s[3:0] $end
$var reg 4 c dig1_s[3:0] $end
$var reg 1 d r_s $end
$upscope $end
$scope module global $end
$var reg 1 e start $end
$var reg 1 f stop_in $end
$var reg 1 g door $end
$var reg 4 h t_in0[3:0] $end
$var reg 4 i t_in1[3:0] $end
$var reg 4 j w_in[3:0] $end
$var reg 1 k enable_out $end
$comment prev_state is not handled $end
$comment next_state is not handled $end
$var integer 32 l t $end
$var integer 32 m w $end
$var integer 32 n safety $end
$var reg 1 o enable $end
$upscope $end
$scope module pot $end
$var reg 1 p w_in $end
$var reg 1 q en $end
$var reg 4 r w_out_0[3:0] $end
$var reg 4 s w_out_1[3:0] $end
$var reg 8 t pot_out[7:0] $end
$comment prev_state is not handled $end
$comment next_state is not handled $end
$var reg 4 u w_out_0_s[3:0] $end
$upscope $end
$upscope $end
$upscope $end
$enddefinitions $end
#0
0!
0"
0#
0$
0%
0&
0'
0(
0)
0*
0+
0,
0-
0.
0/
00
b00000001 1
b0000 2
b0000 3
b0000 4
b0001 5
b0000 6
b0000 7
b0000 8
bUUUU 9
bUUUU :
bUUUU ;
bUUUU <
0=
0>
0?
0@
0A
0B
0C
0D
0E
0F
0G
0H
0I
0J
0K
b0000 L
b0000 M
b0000 N
0O
0P
0Q
b0000 R
b0000 S
b0000 T
b0000 U
b0000 V
b00000000 W
0X
0Y
0Z
U[
b0000 \
b0000 ]
b0000000 ^
b0000 _
b0000 `
b0 a
b0000 b
b0000 c
0d
0e
0f
0g
b0000 h
b0000 i
b0001 j
0k
b0 l
b1010 m
b1010 n
0o
0p
0q
b0000 r
b0001 s
b00000001 t
b0000 u
#500000000000000
1!
1)
1X
#1000000000000000
0!
0)
0X
#1500000000000000
1!
1)
1X
#2000000000000000
0!
1#
0)
1*
1?
1B
1F
1H
b0001 M
0X
#2500000000000000
1!
1)
1X
#3000000000000000
0!
0#
0)
0*
b0001 2
0?
0B
0F
0H
b0001 L
b0001 N
b0001 R
0X
#3500000000000000
1!
1)
1X
#4000000000000000
0!
1#
0)
1*
1?
1B
1F
1H
b0010 M
0X
#4500000000000000
1!
1)
1X
#5000000000000000
0!
0#
0)
0*
b0010 2
0?
0B
0F
0H
b0010 L
b0010 N
b0010 R
0X
#5500000000000000
1!
1)
1X
#6000000000000000
0!
1#
0)
1*
1?
1B
1F
1H
b0011 M
0X
#6500000000000000
1!
1)
1X
#7000000000000000
0!
0#
0)
0*
b0011 2
0?
0B
0F
0H
b0011 L
b0011 N
b0011 R
0X
#7500000000000000
1!
1)
1X
#8000000000000000
0!
0)
0X
#8500000000000000
1!
1)
1X
#9000000000000000
0!
0)
0X
#9500000000000000
1!
1)
1X
#10000000000000000
0!
1"
0)
1+
b0011 4
1=
1A
1E
1J
1Q
b0011 V
b00110000 W
0X
b0011 ]
#10500000000000000
1!
1)
b0011 8
b0011 T
1X
b0011110 ^
b0011 `
b11110 a
b0011 c
b0011 i
b11110 l
b101000 n
#11000000000000000
0!
0"
0)
0+
0=
0A
0E
0J
0Q
0X
#11500000000000000
1!
1)
1X
#12000000000000000
0!
0)
0X
#12500000000000000
1!
1)
1X
#13000000000000000
0!
1#
0)
1*
1?
1B
1F
1H
b0100 M
0X
#13500000000000000
1!
1)
1X
#14000000000000000
0!
0#
0)
0*
b0100 2
0?
0B
0F
0H
b0100 L
b0100 N
b0100 R
0X
#14500000000000000
1!
1)
1X
#15000000000000000
0!
1#
0)
1*
1?
1B
1F
1H
b0101 M
0X
#15500000000000000
1!
1)
1X
#16000000000000000
0!
0#
0)
0*
b0101 2
0?
0B
0F
0H
b0101 L
b0101 N
b0101 R
0X
#16500000000000000
1!
1)
1X
#17000000000000000
0!
1#
0)
1*
1?
1B
1F
1H
b0110 M
0X
#17500000000000000
1!
1)
1X
#18000000000000000
0!
0#
0)
0*
b0110 2
0?
0B
0F
0H
b0110 L
b0110 N
b0110 R
0X
#18500000000000000
1!
1)
1X
#19000000000000000
0!
1#
0)
1*
1?
1B
1F
1H
b0111 M
0X
#19500000000000000
1!
1)
1X
#20000000000000000
0!
0#
0)
0*
b0111 2
0?
0B
0F
0H
b0111 L
b0111 N
b0111 R
0X
#20500000000000000
1!
1)
1X
#21000000000000000
0!
0)
0X
#21500000000000000
1!
1)
1X
#22000000000000000
0!
0)
0X
#22500000000000000
1!
1)
1X
#23000000000000000
0!
1"
0)
1+
b0011 3
b0111 4
1=
1A
1E
1J
1Q
b0011 U
b0111 V
b01110011 W
0X
b0011 \
b0111 ]
#23500000000000000
1!
1)
b0011 7
b0111 8
b0011 S
b0111 T
1X
b1001001 ^
b0011 _
b0111 `
b1001001 a
b0011 b
b0111 c
b0011 h
b0111 i
b1001001 l
b1010011 n
#24000000000000000
0!
0"
0)
0+
0=
0A
0E
0J
0Q
0X
#24500000000000000
1!
1)
1X
#25000000000000000
0!
0)
0X
#25500000000000000
1!
1)
1X
#26000000000000000
0!
1&
1(
0)
1.
1/
1@
1D
1K
b0000 M
1P
0X
1Z
1e
1k
1o
1q
#26500000000000000
1!
1)
b0010 3
b0010 7
b0010 S
b0010 U
b01110010 W
1X
b0010 \
b1001000 ^
b0010 _
b1001000 a
b0010 b
b0010 h
b1001000 l
b1010010 n
#27000000000000000
0!
0&
0)
0/
b0000 2
0K
b0000 L
b0000 N
b0000 R
0X
0e
#27500000000000000
1!
1)
b0001 3
b0001 7
b0001 S
b0001 U
b01110001 W
1X
b0001 \
b1000111 ^
b0001 _
b1000111 a
b0001 b
b0001 h
b1000111 l
b1010001 n
#28000000000000000
0!
0)
0X
#28500000000000000
1!
1)
b0000 3
b0000 7
b0000 S
b0000 U
b01110000 W
1X
b0000 \
b1000110 ^
b0000 _
b1000110 a
b0000 b
b0000 h
b1000110 l
b1010000 n
#29000000000000000
0!
1"
0)
1+
1A
0X
#29500000000000000
1!
1)
b1001 3
b0110 4
b1001 7
b0110 8
b1001 S
b0110 T
b1001 U
b0110 V
b01101001 W
1X
b1001 \
b0110 ]
b1000101 ^
b1001 _
b0110 `
b1000101 a
b1001 b
b0110 c
b1001 h
b0110 i
b1000101 l
b1001111 n
#30000000000000000
0!
0"
0)
0+
0A
0X
#30500000000000000
1!
1)
b1000 3
b1000 7
b1000 S
b1000 U
b01101000 W
1X
b1000 \
b1000100 ^
b1000 _
b1000100 a
b1000 b
b1000 h
b1000100 l
b1001110 n
#31000000000000000
0!
0)
0X
#31500000000000000
1!
1)
b0111 3
b0111 7
b0111 S
b0111 U
b01100111 W
1X
b0111 \
b1000011 ^
b0111 _
b1000011 a
b0111 b
b0111 h
b1000011 l
b1001101 n
#32000000000000000
0!
1#
0)
1*
1B
0X
#32500000000000000
1!
1)
b0110 3
b0110 7
b0110 S
b0110 U
b01100110 W
1X
b0110 \
b1000010 ^
b0110 _
b1000010 a
b0110 b
b0110 h
b1000010 l
b1001100 n
#33000000000000000
0!
0#
0)
0*
0B
0X
#33500000000000000
1!
1)
b0101 3
b0101 7
b0101 S
b0101 U
b01100101 W
1X
b0101 \
b1000001 ^
b0101 _
b1000001 a
b0101 b
b0101 h
b1000001 l
b1001011 n
#34000000000000000
0!
0)
0X
#34500000000000000
1!
1)
b0100 3
b0100 7
b0100 S
b0100 U
b01100100 W
1X
b0100 \
b1000000 ^
b0100 _
b1000000 a
b0100 b
b0100 h
b1000000 l
b1001010 n
#35000000000000000
0!
1$
0)
1-
1C
0X
#35500000000000000
1!
1)
b0011 3
b0011 7
b0011 S
b0011 U
b01100011 W
1X
b0011 \
b0111111 ^
b0011 _
b111111 a
b0011 b
b0011 h
b111111 l
b1001001 n
#36000000000000000
0!
0$
0)
0-
0C
0X
#36500000000000000
1!
1)
b0010 3
b0010 7
b0010 S
b0010 U
b01100010 W
1X
b0010 \
b0111110 ^
b0010 _
b111110 a
b0010 b
b0010 h
b111110 l
b1001000 n
#37000000000000000
0!
0)
0X
#37500000000000000
1!
1)
b0001 3
b0001 7
b0001 S
b0001 U
b01100001 W
1X
b0001 \
b0111101 ^
b0001 _
b111101 a
b0001 b
b0001 h
b111101 l
b1000111 n
#38000000000000000
0!
1%
0(
0)
1,
0.
0@
0D
0P
0X
0Z
1g
0k
0o
0q
