JOUSAMRON MICROONDAS/JOUSAMRON MICROONDAS.srcs/sources_1/imports/sources/State Machines/potencia.vhd
library IEEE;
use IEEE.std_logic_1164.all;

entity potencia is
    port(
    --clk: in std_logic;
    w_in: in std_logic;
    en: in std_logic;
    w_out_0: out STD_LOGIC_VECTOR(3 downto 0);
    w_out_1: out STD_LOGIC_VECTOR(3 downto 0);
    pot_out: out std_logic_vector(7 downto 0)
    );
end entity;

architecture Behavioral of potencia is
    type states is (W1,W2,W3,W4,W5,W6,W7,W8);
    signal prev_state: states:=W1;
    signal next_state: states;
    signal w_out_0_s: STD_LOGIC_VECTOR(3 downto 0):="0000";
    begin

    process(w_in, en)
    begin
     if en='0' then
            if rising_edge(w_in) then
                prev_state <= next_state;
          end if;
     end if;
    end process;


    process(prev_state)
    begin
        case prev_state is
            when W1 => 
                w_out_1 <= "0001";
                next_state<=W2;
                pot_out <= "00000001";
            when W2 => 
                w_out_1 <= "0010";
                next_state<=W3;
                pot_out <= "00000011";
            when W3 => 
                w_out_1 <= "0011";
                next_state<=W4;
                pot_out <= "00000111";
            when W4 => 
                w_out_1 <= "0100";
                next_state<=W5;
                pot_out <= "00001111";
            when W5 => 
                w_out_1 <= "0101";
                next_state<=W6;
                pot_out <= "00011111";
            when W6 => 
                w_out_1 <= "0110";
                next_state<=W7;
                pot_out <= "00111111";
            when W7 =>
                w_out_1 <= "0111"; 
                next_state<=W8;
                pot_out <= "01111111";
            when W8 =>
                w_out_1 <="1000";
                next_state<=W1;
                pot_out <= "11111111";
        end case;
    end process;
    
    

    w_out_0 <= w_out_0_s;
    end Behavioral;

sources/State Machines/global.vhd
library IEEE;
use IEEE.std_logic_1164.all;
use IEEE.numeric_std.all;

entity global is
    port(

      
        start, stop_in : in std_logic;
        door: in std_logic;
        t_in0: in std_logic_vector(3 downto 0);
        t_in1: in std_logic_vector(3 downto 0);

        w_in: in std_logic_vector(3 downto 0);

        enable_out: out std_logic

    );
end entity;

architecture Behavioral of global is
    type states is (running, stopped);
    signal prev_state: states:=stopped;
    signal next_state: states;
    signal t,w,safety: integer:=0;
    signal enable: std_logic;
    begin
    
    process(t_in0, t_in1, w_in, enable)
    begin
--        if rising_edge(stop_in) and enable='0' then
--            t<=0;
--            w<=0;
--            safety<=0;
--        else
        t<= to_integer(unsigned(t_in1))*10 + to_integer(unsigned(t_in0));
        w<= to_integer(unsigned(w_in)*10);
        safety<=to_integer(unsigned(t_in1))*10 + to_integer(unsigned(t_in0))+to_integer(unsigned(w_in)*10);
       -- end if;
        
    end process;
    
    process(prev_state, start, stop_in, door, t,w,safety)

    begin
        if prev_state=running and (door='1' or rising_edge(stop_in) or t=0) then
            prev_state<=next_state;

        elsif prev_state=stopped and (rising_edge(start) and (t>0) and (safety<=100) and (door='0')) then
            prev_state<=next_state;
        end if;

    end process;

    process(prev_state)
    begin
        case prev_state is
            when stopped =>
                next_state <= running;
            when running =>
                next_state <= stopped;
            end case;
    end process;

    enable <= '1' when prev_state=running else '0';
    enable_out<=enable;
    end architecture;

sources/Contadores/cont_des.vhd
library IEEE;
use IEEE.std_logic_1164.all;
use IEEE.numeric_std.all;

entity CONT_2DIG is
    
    port(
        clk: in std_logic;
        reset: in std_logic;
        enable: in std_logic;
      
           sr_r: out std_logic;
        dig_in0, dig_in1: in std_logic_vector(3 downto 0);
        num_out: out std_logic_vector(6 downto 0);
        dig0, dig1: out std_logic_vector(3 downto 0)
        
    );

    end entity;

architecture Behavioral of CONT_2DIG is
    
    signal count: integer range 90 downto 0 := 0;
    signal dig0_s,dig1_s: unsigned(3 downto 0) := (others => '0');
    signal r_s: std_logic:='0';

    begin

    process(clk, enable, count,r_s)
    begin
    
     if enable='0' then
   
        count <= to_integer(unsigned(dig_in1))*10 + to_integer(unsigned(dig_in0));
            dig0_s <= unsigned(dig_in0); 
            dig1_s <= unsigned(dig_in1);

      
    elsif enable='1' then    
         
        if rising_edge(clk) and count>0 then

            count <= count - 1;
            if dig0_s=0 then
                dig0_s <= to_unsigned(9,4);
                dig1_s <= dig1_s - 1;
            else 
                dig0_s <= dig0_s - 1;
            end if;
            
--            if count-1 = 0 then
--            sr_r<='1';
--            else
--            sr_r<='0';
--            end if;
            
        end if;         
     end if;

    end process;
    
    dig0 <= std_logic_vector(dig0_s);
    dig1 <= std_logic_vector(dig1_s);
    
  
    num_out <= std_logic_vector(to_unsigned(count,7));
    end architecture;

sources/SR_SP.vhd

library IEEE;
use IEEE.std_logic_1164.all;
use IEEE.numeric_std.all;

entity SR_SER_PAR is

port ( r, en : in std_logic;
      clk : in std_logic;

      d : in std_logic_vector(3 downto 0);
      d_in0, d_in1 : in std_logic_vector(3 downto 0);
      q_out0, q_out1 : out std_logic_vector(3 downto 0));

end entity;

architecture Behavioral of SR_SER_PAR is
    

        signal q: std_logic_vector(7 downto 0):="00000000";

        begin

        process(clk,r,en,d,q,d_in1,d_in0)
        begin
                 
        if(r='1' and en='0') then
   
                --q<="00000000"; 


            elsif r='0' and en='0' then
                if(rising_edge(clk)) then
                for i in 0 to 3 loop
                  q(3-i)<=q(7-i);
                  q(7-i)<=d(3-i);
                 
                end loop;
    
                end if;
            elsif r='0' and en='1' then
                q(7 downto 4)<=d_in1;
                q(3 downto 0)<=d_in0;
            end if;
        end process;
        q_out0<=q(3 downto 0);
        q_out1<=q(7 downto 4);
    end architecture;

sources/Contadores/cont_0a9.vhd
library IEEE;
use IEEE.std_logic_1164.all;
use IEEE.numeric_std.all;

entity contador0a9 is
    port (
        sr_in: in std_logic_vector(3 downto 0);
        t_in, rst, load, start: in std_logic;
        t_out: out std_logic_vector(3 downto 0)

        );

end entity;

architecture contador0a9 of contador0a9 is
    
    signal contador : unsigned(3 downto 0) := (others => '0');
    signal t_out_s: std_logic_vector(3 downto 0):= (others => '0');

    
    begin
        process(t_in, rst,load, start, sr_in)
        begin

            if rst='1' or start='1' then
                contador <= (others => '0');

              
            elsif rst='0' then 
                if  rising_edge(t_in) then
                    if contador >= 9 then
                        contador <= (others => '0');
                    else
                        contador <= contador + 1;
                        
                    end if;
                    
                end if;  
            end if;            
         
            if falling_edge(load) and sr_in=t_out_s then
                contador <= (others => '0');
            end if;
         
        end process;
        t_out_s <= std_logic_vector(contador);
        t_out <= t_out_s;

    end architecture;

sources/enable.vhd
library IEEE;
use IEEE.std_logic_1164.all;
use IEEE.numeric_std.all;

entity enable_block is
    port(

        en  : in std_logic;
        
        load, t, w: in std_logic;
        load_o, t_o, w_o: out std_logic;
        
        start, stop_in: in std_logic;
        start_o, stop_o, rst_o: out std_logic
    );
end entity;


architecture Behavioral of enable_block is

    signal stop_s: std_logic:='0';
    begin


    load_o<=load WHEN en='0' ELSE '0';
    t_o<=t WHEN en='0' ELSE '0';
    w_o<=w WHEN en='0' ELSE '0';

    start_o<=start;
    
    -- stop_o<=stop_in WHEN en='1' ELSE '0';
    -- rst_o<=stop_in WHEN  en='0' ELSE '0';


end architecture;

sources/mainT.vhd
library IEEE;
use IEEE.std_logic_1164.all;
use IEEE.numeric_std.all;

entity mainT is
    port(
        clk1hz : in std_logic;
        t_in, load, door,w : in std_logic;
        en: out std_logic;
        start,stop_in: in std_logic;
        --SAL_7SEG : out std_logic_vector(6 downto 0);
        --ANODOS: out std_logic_vector(3 downto 0);
        LED:out std_logic_vector(7 downto 0)
    );
end entity;

architecture Behavioral of mainT is

    --signal clk1hz, clk200khz: std_logic;
    
    signal t_in_s,t_in0, t_in1: std_logic_vector(3 downto 0);
  
    signal w_1, w_0: std_logic_vector(3 downto 0);
    
    signal dig0_out, dig1_out: std_logic_vector(3 downto 0);
    
    signal BCD1, BCD2, BCD3, BCD4: std_logic_vector(3 downto 0);

    signal load_s, w_s, t_s, start_s, stop_s, rst_s: std_logic;

    signal enable: std_logic;
    begin 
    

    
    -- clk1: entity work.DIV_1HZ
    --     port map(
    --         clk => clk,
    --         CLK_o => clk1hz
    --     );

    -- clk200k: entity work.DIV_VD
    --     port map(
    --         clk => clk,
    --         CLK_o => clk200khz
    --     );


    en_block: entity work.enable_block
        port map(

            en=> enable,
            
            load=>load,
            t=>t_in,
            w=>w,

            load_o=>load_s,
            w_o=>w_s,
            t_o=>t_s,

            start=>start,
            stop_in=>stop_in,

            start_o=>start_s,
            stop_o=>stop_s,
            rst_o=>rst_s
        );

    cont0a9: entity work.contador0a9 
        port map(
            t_in => t_s,
            sr_in => t_in1,
            start=>start_s,
            load=>load_s,
            rst => rst_s,

            t_out => t_in_s
        );
    
        sr: entity work.SR_SER_PAR
        port map(
            r => rst_s,
           
            en=>enable,
            clk=> load_s,
            d=> t_in_s,
            d_in0=> dig0_out,
            d_in1=> dig1_out,
            q_out0=> t_in0,
            q_out1=> t_in1
        );

    cont_des: entity  work.CONT_2DIG
        port map(
            clk => clk1hz,
            reset => rst_s,
            enable => enable,

            dig_in0 => t_in0,
            dig_in1 => t_in1,

            num_out => open,

            dig0 => dig0_out,
            dig1 => dig1_out
        );

    global: entity work.global
        port map(

           
            start => start_s,
            stop_in => stop_s,
            door => door,
            
            w_in => w_1,
            
            t_in0 => dig0_out,
            t_in1 => dig1_out,

            enable_out => enable
        );
    
    pot: entity work.potencia
        port map(

            w_in => w_s,
            en=> enable,
            w_out_0 => w_0,
            w_out_1 => w_1,
            pot_out=> LED
        );

        -- VD: entity work.VIS_DIN_4DIG
        
        -- port map(
        -- clk=> clk200khz,
        -- ANODS=> ANODOS,
        -- SAL7SEG=> SAL_7SEG,
        -- BCD1=>dig1_out,
        -- BCD2=>dig0_out,
        -- BCD3=>w_1,
        -- BCD4=>w_0
        -- );
        en<=enable;
end architecture;

sources/Test/testbench-main.vhd
library IEEE;
use IEEE.std_logic_1164.all;
use IEEE.numeric_std.all;

entity testbench is
end entity;

architecture behavioral of testbench is
    
    signal clk: std_logic := '0';
    signal clk_period: time := 1 sec;


    signal load,t,w,door,start,stop_in,en: std_logic := '0';

    begin

    main: entity work.mainT
        port map(
            clk1hz => clk,
            load => load,
            t_in => t,
            w=> w,
            door => door,
            start => start,
            stop_in => stop_in,
            en => en

        );
    
        CLK_1HZ : process
    begin
    wait for clk_period / 2;
    if clk = '1' then
        clk <= '0';
    else
        clk <= '1';
    end if;
    end process;

    process
    begin

        wait for 2 sec;
        for i in 0 to 2 loop
        t<= '1';
        wait for 1 sec;
        t<= '0';    
        wait for 1 sec;
        end loop;

        wait for 2 sec;

        load <= '1';
        wait for 1 sec;
        load <= '0';

        wait for 2 sec;

        for i in 0 to 3 loop
        t<= '1';
        wait for 1 sec;
        t<= '0';    
        wait for 1 sec;
        end loop;

        wait for 2 sec;

        load <= '1';
        wait for 1 sec;
        load <= '0';

        wait for 2 sec;

        start <= '1';
        wait for 1 sec;
        start <= '0';


        wait for 2 sec;

        load <= '1';
        wait for 1 sec;
        load <= '0';


        wait for 2 sec;

        t <= '1';
        wait for 1 sec;
        t <= '0';


        wait for 2 sec;

        w <= '1';
        wait for 1 sec;
        w <= '0';


        wait for 2 sec;

        door <= '1';
        wait for 2 sec;
        door <= '0';
        
        wait for 2 sec;

        start <= '1';
        wait for 1 sec;
        start <= '0';

        wait for 2 sec;

        stop_in <= '1';
        wait for 1 sec;
        stop_in <= '0';

    wait;
    end process;    
end architecture;

sources/Dumps/main-dump.vcd
$date
  Thu May 25 00:13:21 2023
$end
$version
  GHDL v0
$end
$timescale
  1 fs
$end
$scope module standard $end
$upscope $end
$scope module std_logic_1164 $end
$upscope $end
$scope module numeric_std $end
$upscope $end
$scope module testbench $end
$var reg 1 ! clk $end
$comment clk_period is not handled $end
$var reg 1 " load $end
$var reg 1 # t $end
$var reg 1 $ w $end
$var reg 1 % door $end
$var reg 1 & start $end
$var reg 1 ' stop_in $end
$var reg 1 ( en $end
$scope module main $end
$var reg 1 ) clk1hz $end
$var reg 1 * t_in $end
$var reg 1 + load $end
$var reg 1 , door $end
$var reg 1 - w $end
$var reg 1 . en $end
$var reg 1 / start $end
$var reg 1 0 stop_in $end
$var reg 8 1 led[7:0] $end
$var reg 4 2 t_in_s[3:0] $end
$var reg 4 3 t_in0[3:0] $end
$var reg 4 4 t_in1[3:0] $end
$var reg 4 5 w_1[3:0] $end
$var reg 4 6 w_0[3:0] $end
$var reg 4 7 dig0_out[3:0] $end
$var reg 4 8 dig1_out[3:0] $end
$var reg 4 9 bcd1[3:0] $end
$var reg 4 : bcd2[3:0] $end
$var reg 4 ; bcd3[3:0] $end
$var reg 4 < bcd4[3:0] $end
$var reg 1 = load_s $end
$var reg 1 > w_s $end
$var reg 1 ? t_s $end
$var reg 1 @ start_s $end
$var reg 1 A stop_s $end
$var reg 1 B rst_s $end
$var reg 1 C enable $end
$scope module en_block $end
$var reg 1 D en $end
$var reg 1 E load $end
$var reg 1 F t $end
$var reg 1 G w $end
$var reg 1 H load_o $end
$var reg 1 I t_o $end
$var reg 1 J w_o $end
$var reg 1 K start $end
$var reg 1 L stop_in $end
$var reg 1 M start_o $end
$var reg 1 N stop_o $end
$var reg 1 O rst_o $end
$var reg 1 P stop_s $end
$upscope $end
$scope module cont0a9 $end
$var reg 4 Q sr_in[3:0] $end
$var reg 1 R t_in $end
$var reg 1 S rst $end
$var reg 1 T load $end
$var reg 1 U start $end
$var reg 4 V t_out[3:0] $end
$var reg 4 W contador[3:0] $end
$var reg 4 X t_out_s[3:0] $end
$upscope $end
$scope module sr $end
$var reg 1 Y r $end
$var reg 1 Z en $end
$var reg 1 [ clk $end
$var reg 4 \ d[3:0] $end
$var reg 4 ] d_in0[3:0] $end
$var reg 4 ^ d_in1[3:0] $end
$var reg 4 _ q_out0[3:0] $end
$var reg 4 ` q_out1[3:0] $end
$var reg 8 a q[7:0] $end
$upscope $end
$scope module cont_des $end
$var reg 1 b clk $end
$var reg 1 c reset $end
$var reg 1 d enable $end
$var reg 1 e sr_r $end
$var reg 4 f dig_in0[3:0] $end
$var reg 4 g dig_in1[3:0] $end
$var reg 7 h num_out[6:0] $end
$var reg 4 i dig0[3:0] $end
$var reg 4 j dig1[3:0] $end
$var integer 32 k count $end
$var reg 4 l dig0_s[3:0] $end
$var reg 4 m dig1_s[3:0] $end
$var reg 1 n r_s $end
$upscope $end
$scope module global $end
$var reg 1 o start $end
$var reg 1 p stop_in $end
$var reg 1 q door $end
$var reg 4 r t_in0[3:0] $end
$var reg 4 s t_in1[3:0] $end
$var reg 4 t w_in[3:0] $end
$var reg 1 u enable_out $end
$comment prev_state is not handled $end
$comment next_state is not handled $end
$var integer 32 v t $end
$var integer 32 w w $end
$var integer 32 x safety $end
$var reg 1 y enable $end
$upscope $end
$scope module pot $end
$var reg 1 z w_in $end
$var reg 1 { en $end
$var reg 4 | w_out_0[3:0] $end
$var reg 4 } w_out_1[3:0] $end
$var reg 8 !" pot_out[7:0] $end
$comment prev_state is not handled $end
$comment next_state is not handled $end
$var reg 4 "" w_out_0_s[3:0] $end
$upscope $end
$upscope $end
$upscope $end
$enddefinitions $end
#0
0!
0"
0#
0$
0%
0&
0'
0(
0)
0*
0+
0,
0-
0.
0/
00
b00000001 1
b0000 2
b0000 3
b0000 4
b0001 5
b0000 6
b0000 7
b0000 8
bUUUU 9
bUUUU :
bUUUU ;
bUUUU <
0=
0>
0?
0@
0A
0B
0C
0D
0E
0F
0G
0H
0I
0J
0K
0L
0M
0N
0O
0P
b0000 Q
0R
0S
0T
0U
b0000 V
b0000 W
b0000 X
0Y
0Z
0[
b0000 \
b0000 ]
b0000 ^
b0000 _
b0000 `
b00000000 a
0b
0c
0d
Ue
b0000 f
b0000 g
b0000000 h
b0000 i
b0000 j
b0 k
b0000 l
b0000 m
0n
0o
0p
0q
b0000 r
b0000 s
b0001 t
0u
b0 v
b1010 w
b1010 x
0y
0z
0{
b0000 |
b0001 }
b00000001 !"
b0000 ""
#500000000000000
1!
1)
1b
#1000000000000000
0!
0)
0b
#1500000000000000
1!
1)
1b
#2000000000000000
0!
1#
0)
1*
b0001 2
1?
1F
1I
1R
b0001 V
b0001 W
b0001 X
b0001 \
0b
#2500000000000000
1!
1)
1b
#3000000000000000
0!
0#
0)
0*
0?
0F
0I
0R
0b
#3500000000000000
1!
1)
1b
#4000000000000000
0!
1#
0)
1*
b0010 2
1?
1F
1I
1R
b0010 V
b0010 W
b0010 X
b0010 \
0b
#4500000000000000
1!
1)
1b
#5000000000000000
0!
0#
0)
0*
0?
0F
0I
0R
0b
#5500000000000000
1!
1)
1b
#6000000000000000
0!
1#
0)
1*
b0011 2
1?
1F
1I
1R
b0011 V
b0011 W
b0011 X
b0011 \
0b
#6500000000000000
1!
1)
1b
#7000000000000000
0!
0#
0)
0*
0?
0F
0I
0R
0b
#7500000000000000
1!
1)
1b
#8000000000000000
0!
0)
0b
#8500000000000000
1!
1)
1b
#9000000000000000
0!
0)
0b
#9500000000000000
1!
1)
1b
#10000000000000000
0!
1"
0)
1+
b0011 4
1=
1E
1H
b0011 Q
1T
1[
b0011 `
b00110000 a
0b
b0011 g
#10500000000000000
1!
1)
b0011 8
b0011 ^
1b
b0011110 h
b0011 j
b11110 k
b0011 m
b0011 s
b11110 v
b101000 x
#11000000000000000
0!
0"
0)
0+
b0000 2
0=
0E
0H
0T
b0000 V
b0000 W
b0000 X
0[
b0000 \
0b
#11500000000000000
1!
1)
1b
#12000000000000000
0!
0)
0b
#12500000000000000
1!
1)
1b
#13000000000000000
0!
1#
0)
1*
b0001 2
1?
1F
1I
1R
b0001 V
b0001 W
b0001 X
b0001 \
0b
#13500000000000000
1!
1)
1b
#14000000000000000
0!
0#
0)
0*
0?
0F
0I
0R
0b
#14500000000000000
1!
1)
1b
#15000000000000000
0!
1#
0)
1*
b0010 2
1?
1F
1I
1R
b0010 V
b0010 W
b0010 X
b0010 \
0b
#15500000000000000
1!
1)
1b
#16000000000000000
0!
0#
0)
0*
0?
0F
0I
0R
0b
#16500000000000000
1!
1)
1b
#17000000000000000
0!
1#
0)
1*
b0011 2
1?
1F
1I
1R
b0011 V
b0011 W
b0011 X
b0011 \
0b
#17500000000000000
1!
1)
1b
#18000000000000000
0!
0#
0)
0*
0?
0F
0I
0R
0b
#18500000000000000
1!
1)
1b
#19000000000000000
0!
1#
0)
1*
b0100 2
1?
1F
1I
1R
b0100 V
b0100 W
b0100 X
b0100 \
0b
#19500000000000000
1!
1)
1b
#20000000000000000
0!
0#
0)
0*
0?
0F
0I
0R
0b
#20500000000000000
1!
1)
1b
#21000000000000000
0!
0)
0b
#21500000000000000
1!
1)
1b
#22000000000000000
0!
0)
0b
#22500000000000000
1!
1)
1b
#23000000000000000
0!
1"
0)
1+
b0011 3
b0100 4
1=
1E
1H
b0100 Q
1T
1[
b0011 _
b0100 `
b01000011 a
0b
b0011 f
b0100 g
#23500000000000000
1!
1)
b0011 7
b0100 8
b0011 ]
b0100 ^
1b
b0101011 h
b0011 i
b0100 j
b101011 k
b0011 l
b0100 m
b0011 r
b0100 s
b101011 v
b110101 x
#24000000000000000
0!
0"
0)
0+
b0000 2
0=
0E
0H
0T
b0000 V
b0000 W
b0000 X
0[
b0000 \
0b
#24500000000000000
1!
1)
1b
#25000000000000000
0!
0)
0b
#25500000000000000
1!
1)
1b
#26000000000000000
0!
1&
1(
0)
1.
1/
1@
1C
1D
1K
1M
1U
1Z
0b
1d
1o
1u
1y
1{
#26500000000000000
1!
1)
b0010 3
b0010 7
b0010 ]
b0010 _
b01000010 a
1b
b0010 f
b0101010 h
b0010 i
b101010 k
b0010 l
b0010 r
b101010 v
b110100 x
#27000000000000000
0!
0&
0)
0/
0@
0K
0M
0U
0b
0o
#27500000000000000
1!
1)
b0001 3
b0001 7
b0001 ]
b0001 _
b01000001 a
1b
b0001 f
b0101001 h
b0001 i
b101001 k
b0001 l
b0001 r
b101001 v
b110011 x
#28000000000000000
0!
0)
0b
#28500000000000000
1!
1)
b0000 3
b0000 7
b0000 ]
b0000 _
b01000000 a
1b
b0000 f
b0101000 h
b0000 i
b101000 k
b0000 l
b0000 r
b101000 v
b110010 x
#29000000000000000
0!
1"
0)
1+
1E
0b
#29500000000000000
1!
1)
b1001 3
b0011 4
b1001 7
b0011 8
b0011 Q
b1001 ]
b0011 ^
b1001 _
b0011 `
b00111001 a
1b
b1001 f
b0011 g
b0100111 h
b1001 i
b0011 j
b100111 k
b1001 l
b0011 m
b1001 r
b0011 s
b100111 v
b110001 x
#30000000000000000
0!
0"
0)
0+
0E
0b
#30500000000000000
1!
1)
b1000 3
b1000 7
b1000 ]
b1000 _
b00111000 a
1b
b1000 f
b0100110 h
b1000 i
b100110 k
b1000 l
b1000 r
b100110 v
b110000 x
#31000000000000000
0!
0)
0b
#31500000000000000
1!
1)
b0111 3
b0111 7
b0111 ]
b0111 _
b00110111 a
1b
b0111 f
b0100101 h
b0111 i
b100101 k
b0111 l
b0111 r
b100101 v
b101111 x
#32000000000000000
0!
1#
0)
1*
1F
0b
#32500000000000000
1!
1)
b0110 3
b0110 7
b0110 ]
b0110 _
b00110110 a
1b
b0110 f
b0100100 h
b0110 i
b100100 k
b0110 l
b0110 r
b100100 v
b101110 x
#33000000000000000
0!
0#
0)
0*
0F
0b
#33500000000000000
1!
1)
b0101 3
b0101 7
b0101 ]
b0101 _
b00110101 a
1b
b0101 f
b0100011 h
b0101 i
b100011 k
b0101 l
b0101 r
b100011 v
b101101 x
#34000000000000000
0!
0)
0b
#34500000000000000
1!
1)
b0100 3
b0100 7
b0100 ]
b0100 _
b00110100 a
1b
b0100 f
b0100010 h
b0100 i
b100010 k
b0100 l
b0100 r
b100010 v
b101100 x
#35000000000000000
0!
1$
0)
1-
1G
0b
#35500000000000000
1!
1)
b0011 3
b0011 7
b0011 ]
b0011 _
b00110011 a
1b
b0011 f
b0100001 h
b0011 i
b100001 k
b0011 l
b0011 r
b100001 v
b101011 x
#36000000000000000
0!
0$
0)
0-
0G
0b
#36500000000000000
1!
1)
b0010 3
b0010 7
b0010 ]
b0010 _
b00110010 a
1b
b0010 f
b0100000 h
b0010 i
b100000 k
b0010 l
b0010 r
b100000 v
b101010 x
#37000000000000000
0!
0)
0b
#37500000000000000
1!
1)
b0001 3
b0001 7
b0001 ]
b0001 _
b00110001 a
1b
b0001 f
b0011111 h
b0001 i
b11111 k
b0001 l
b0001 r
b11111 v
b101001 x
#38000000000000000
0!
1%
0(
0)
1,
0.
0C
0D
0Z
0b
0d
1q
0u
0y
0{
#38500000000000000
1!
1)
1b
#39000000000000000
0!
0)
0b
#39500000000000000
1!
1)
1b
#40000000000000000
0!
0%
0)
0,
0b
0q
#40500000000000000
1!
1)
1b
#41000000000000000
0!
0)
0b
#41500000000000000
1!
1)
1b
#42000000000000000
0!
1&
1(
0)
1.
1/
1@
1C
1D
1K
1M
1U
1Z
0b
1d
1o
1u
1y
1{
#42500000000000000
1!
1)
b0000 3
b0000 7
b0000 ]
b0000 _
b00110000 a
1b
b0000 f
b0011110 h
b0000 i
b11110 k
b0000 l
b0000 r
b11110 v
b101000 x
#43000000000000000
0!
0&
0)
0/
0@
0K
0M
0U
0b
0o
#43500000000000000
1!
1)
b1001 3
b0010 4
b1001 7
b0010 8
b0010 Q
b1001 ]
b0010 ^
b1001 _
b0010 `
b00101001 a
1b
b1001 f
b0010 g
b0011101 h
b1001 i
b0010 j
b11101 k
b1001 l
b0010 m
b1001 r
b0010 s
b11101 v
b100111 x
#44000000000000000
0!
0)
0b
#44500000000000000
1!
1)
b1000 3
b1000 7
b1000 ]
b1000 _
b00101000 a
1b
b1000 f
b0011100 h
b1000 i
b11100 k
b1000 l
b1000 r
b11100 v
b100110 x
#45000000000000000
0!
1'
0)
10
1L
0b
#45500000000000000
1!
1)
b0111 3
b0111 7
b0111 ]
b0111 _
b00100111 a
1b
b0111 f
b0011011 h
b0111 i
b11011 k
b0111 l
b0111 r
b11011 v
b100101 x
#46000000000000000
0!
0'
0(
0)
0.
00
0A
0C
0D
0L
0N
0P
0Z
0b
0d
0p
0u
0y
0{
